LICENSE
README.md
setup.py
micropython_sc16is7xx.egg-info/PKG-INFO
micropython_sc16is7xx.egg-info/SOURCES.txt
micropython_sc16is7xx.egg-info/dependency_links.txt
micropython_sc16is7xx.egg-info/top_level.txt
sc16is7xx/__init__.py
sc16is7xx/sc16is750.py