Metadata-Version: 2.1
Name: micropython-sc16is7xx
Version: 0.0.0
Summary: Library for sc16is7xx
Home-page: https://github.com/petrkr/micropython-sc16is7xx
Author: Petr Kracik
Author-email: petrkr@petrkr.net
License: MIT
Platform: UNKNOWN
Classifier: Programming Language :: Python :: 3
Classifier: License :: OSI Approved :: MIT License
Classifier: Operating System :: OS Independent
Classifier: Development Status :: 3 - Alpha
Requires-Python: >=3.4
License-File: LICENSE
